d8s_strings/__init__.py
d8s_strings/strings.py
tests/__init__.py
tests/test_strings.py
d8s_strings-0.5.0.dist-info/COPYING
d8s_strings-0.5.0.dist-info/COPYING.LESSER
d8s_strings-0.5.0.dist-info/METADATA
d8s_strings-0.5.0.dist-info/WHEEL
d8s_strings-0.5.0.dist-info/top_level.txt
d8s_strings-0.5.0.dist-info/zip-safe
d8s_strings-0.5.0.dist-info/RECORD
