Metadata-Version: 2.1
Name: d8s-strings
Version: 0.5.0
Summary: Democritus functions for working with Python strings.
Home-page: https://github.com/democritus-project/d8s-strings
Author: Floyd Hightower
Author-email: floyd.hightower27@gmail.com
License: GNU Lesser General Public License v3
Keywords: democritus,utility,python,python-strings,python-strings-utility,python-strings
Platform: UNKNOWN
Classifier: Development Status :: 2 - Pre-Alpha
Classifier: Intended Audience :: Developers
Classifier: License :: OSI Approved :: GNU Lesser General Public License v3 or later (LGPLv3+)
Classifier: Natural Language :: English
Classifier: Programming Language :: Python :: 3
Classifier: Programming Language :: Python :: 3.4
Classifier: Programming Language :: Python :: 3.5
Classifier: Programming Language :: Python :: 3.6
Classifier: Programming Language :: Python :: 3.7
Classifier: Programming Language :: Python :: 3.8
Classifier: Programming Language :: Python :: 3.9
Requires-Dist: d8s-hypothesis (==0.*)
Requires-Dist: d8s-uuids (==0.*)
Requires-Dist: d8s-lists (==0.8.0)
Requires-Dist: hypothesis
Requires-Dist: inflect
Requires-Dist: more-itertools
Requires-Dist: d8s-dicts (==0.6.0)
Requires-Dist: d8s-math (==0.7.0)
Requires-Dist: importlib-metadata ; python_version < "3.8"
